hu/__init__.py
hu/_version.py
hu/dotted_dict.py
hu/object_dict.py
hu-0.9.0.dist-info/LICENSE
hu-0.9.0.dist-info/WHEEL
hu-0.9.0.dist-info/METADATA
hu-0.9.0.dist-info/RECORD
