Metadata-Version: 2.1
Name: hu
Version: 0.9.0
Summary: Helpful utility software for open source programmers
Author: Steve Holden
Author-email: steve@holdenweb.com
Requires-Python: >=3.6,<4.0
Classifier: Programming Language :: Python :: 3
Classifier: Programming Language :: Python :: 3.6
Classifier: Programming Language :: Python :: 3.7
Classifier: Programming Language :: Python :: 3.8
